rbnics/__init__.py
rbnics/backends/__init__.py
rbnics/backends/abstract/__init__.py
rbnics/backends/abstract/abs.py
rbnics/backends/abstract/affine_expansion_storage.py
rbnics/backends/abstract/assign.py
rbnics/backends/abstract/basis_functions_matrix.py
rbnics/backends/abstract/copy.py
rbnics/backends/abstract/eigen_solver.py
rbnics/backends/abstract/evaluate.py
rbnics/backends/abstract/export.py
rbnics/backends/abstract/function.py
rbnics/backends/abstract/functions_list.py
rbnics/backends/abstract/gram_schmidt.py
rbnics/backends/abstract/high_order_proper_orthogonal_decomposition.py
rbnics/backends/abstract/import_.py
rbnics/backends/abstract/linear_program_solver.py
rbnics/backends/abstract/linear_solver.py
rbnics/backends/abstract/matrix.py
rbnics/backends/abstract/max.py
rbnics/backends/abstract/mesh_motion.py
rbnics/backends/abstract/non_affine_expansion_storage.py
rbnics/backends/abstract/nonlinear_solver.py
rbnics/backends/abstract/parametrized_expression_factory.py
rbnics/backends/abstract/parametrized_tensor_factory.py
rbnics/backends/abstract/product.py
rbnics/backends/abstract/proper_orthogonal_decomposition.py
rbnics/backends/abstract/reduced_mesh.py
rbnics/backends/abstract/reduced_vertices.py
rbnics/backends/abstract/separated_parametrized_form.py
rbnics/backends/abstract/snapshots_matrix.py
rbnics/backends/abstract/sum.py
rbnics/backends/abstract/symbolic_parameters.py
rbnics/backends/abstract/tensor_basis_list.py
rbnics/backends/abstract/tensor_snapshots_list.py
rbnics/backends/abstract/tensors_list.py
rbnics/backends/abstract/time_quadrature.py
rbnics/backends/abstract/time_series.py
rbnics/backends/abstract/time_stepping.py
rbnics/backends/abstract/transpose.py
rbnics/backends/abstract/vector.py
rbnics/backends/basic/__init__.py
rbnics/backends/basic/basis_functions_matrix.py
rbnics/backends/basic/copy.py
rbnics/backends/basic/evaluate.py
rbnics/backends/basic/export.py
rbnics/backends/basic/functions_list.py
RBniCS-0.2.0.dist-info/AUTHORS
RBniCS-0.2.0.dist-info/COPYING
RBniCS-0.2.0.dist-info/METADATA
RBniCS-0.2.0.dist-info/WHEEL
RBniCS-0.2.0.dist-info/top_level.txt
RBniCS-0.2.0.dist-info/RECORD
