Metadata-Version: 2.1
Name: RBniCS
Version: 0.2.0
Summary: Reduced order modelling in FEniCS
Home-page: https://www.rbnicsproject.org
Author: Francesco Ballarin (and contributors)
Author-email: francesco.ballarin@unicatt.it
License: GNU Library or Lesser General Public License (LGPL)
Classifier: Development Status :: 5 - Production/Stable
Classifier: Intended Audience :: Developers
Classifier: Intended Audience :: Science/Research
Classifier: Programming Language :: Python :: 3
Classifier: Programming Language :: Python :: 3.7
Classifier: Programming Language :: Python :: 3.8
Classifier: Programming Language :: Python :: 3.9
Classifier: Programming Language :: Python :: 3.10
Classifier: Programming Language :: Python :: 3.11
Classifier: Programming Language :: Python :: 3.12
Classifier: License :: OSI Approved :: GNU Library or Lesser General Public License (LGPL)
Classifier: Topic :: Scientific/Engineering :: Mathematics
Classifier: Topic :: Software Development :: Libraries :: Python Modules
License-File: COPYING
License-File: AUTHORS
Requires-Dist: cvxopt >=1.3.1
Requires-Dist: matplotlib
Requires-Dist: mpi4py
Requires-Dist: multipledispatch >=0.5.0
Requires-Dist: scipy
Requires-Dist: sympy >=1.0
Provides-Extra: tests
Requires-Dist: pytest ; extra == 'tests'
Requires-Dist: pytest-benchmark ; extra == 'tests'
